{
    "/user/updateMe": {
        "patch": {
            "tags": ["User"],
            "summary": "Update current user (name, email, image)",
            "security": [{ "bearerAuth": [] }],
            "requestBody": {
                "required": true,
                "content": {
                    "multipart/form-data": {
                        "schema": { "$ref": "#/components/schemas/UpdateMeRequest" }
                    }
                }
            },
            "responses": {
                "200": {
                    "description": "Updated user",
                    "content": {
                        "application/json": {
                            "schema": { "$ref": "#/components/schemas/GetUserByIdResponse" }
                        }
                    }
                },
                "400": { "description": "Bad request" },
                "401": { "description": "Unauthorized" },
                "404": { "description": "User not found" },
                "500": { "description": "Internal Server Error" }
            }
        }
    }
}
