{
    "TechService": {
        "type": "object",
        "properties": {
            "_id": { "type": "string" },
            "user": { "$ref": "#/components/schemas/User" },
            "title": { "type": "string" },
            "description": { "type": "string" },
            "price": { "type": "number", "minimum": 0 },
            "images": { "type": "array", "items": { "$ref": "#/components/schemas/ImageObject" } },
            "ratingsAverage": { "type": "number", "minimum": 1, "maximum": 5 },
            "category": { "$ref": "#/components/schemas/Category" },
            "ratingsQuantity": { "type": "integer" },
            "availabity": {
                "type": "array",
                "items": { "$ref": "#/components/schemas/Availabity" }
            },
            "createdAt": { "type": "string", "format": "date-time" },
            "updatedAt": { "type": "string", "format": "date-time" }
        }
    }
}
